simple_azure_blob_downloader/__init__.py
simple_azure_blob_downloader/download_azure_blob.py
simple_azure_blob_downloader-0.1.0.dist-info/entry_points.txt
simple_azure_blob_downloader-0.1.0.dist-info/WHEEL
simple_azure_blob_downloader-0.1.0.dist-info/METADATA
simple_azure_blob_downloader-0.1.0.dist-info/RECORD
