Metadata-Version: 2.1
Name: simple-azure-blob-downloader
Version: 0.1.0
Summary: 
Author: Jackie Tung
Author-email: jackie@outerbounds.co
Requires-Python: >=3.6,<4.0
Classifier: Programming Language :: Python :: 3
Classifier: Programming Language :: Python :: 3.10
Classifier: Programming Language :: Python :: 3.6
Classifier: Programming Language :: Python :: 3.7
Classifier: Programming Language :: Python :: 3.8
Classifier: Programming Language :: Python :: 3.9
Requires-Dist: azure-identity (>=1.10.0)
Requires-Dist: azure-storage-blob (>=12.12.0)
